{
    "url": "https://www.youtube.com/@covertgoblue",
    "id": "UC-UZjHl2kZ-6XKBLgbFgGAQ",
    "title": "CovertGoBlue",
    "description": "The One in Best-of-One\n\n",
    "tags": [
        "covertgo",
        "magic the gathering",
        "mtg",
        "mtg arena",
        "mtga"
    ],
    "subscribers": 226000,
    "scrape_time": "2024-11-03 01:05:39",
    "videos": [
        {
            "id": "Fc7rjZ3mGRo",
            "url": "https://www.youtube.com/watch?v=Fc7rjZ3mGRo",
            "author": "CovertGoBlue",
            "title": "MTG Restricted List BREAKS Yu-Gi-Oh! Player",
            "description": "I show Cimo the first-ever mtg restricted list from 1994, and he now he needs theropy.\n\nInsert a descriptive sentence about the video\n\nSponsors\n\nCoolStuffInc.com Promo Code CGB5 - https://www.coolstuffinc.com/cgb\nUltimate Guard - https://tinyurl.com/UGCGB\nDripShop.live - https://join.dripshop.live/CovertGoBlue\nMoxfield - https://www.moxfield.com/users/CovertGoBlue\n\nDiscord - https://discord.gg/MXt3DEP\nInstagram - https://www.instagram.com/covertgoblue/\n\nCredits\n\nWritten and performed by Daniel Wagner, aka CovertGoBlue\nEdited by @libmae_\nLogo design by HolyMTG - HolyMTG@gmail.com Twitter @HolyMTG\n© CovertGoBlue Entertainment, LLC\n\n#cgb #mtgarena #mtgstandard",
            "keywords": [
                "Best Deck",
                "Best MTG Deck",
                "CGB",
                "CGB Deck",
                "CGB Magic the Gathering",
                "Covert Go",
                "Covert Go Blue",
                "Covert Go MTG",
                "CovertGoBlue",
                "Deck",
                "Gameplay",
                "MTG Cards",
                "MTG Deck",
                "Mythic",
                "New Cards",
                "New Deck",
                "blb mtg arena",
                "cimo",
                "covertgo",
                "covertgo mtg",
                "deck",
                "decks",
                "demonic tutor",
                "dingus egg",
                "dsk cards",
                "dsk early access",
                "dsk mtg",
                "duskmourn standard",
                "early access",
                "gameplay",
                "guide",
                "magic the gathering",
                "mtg",
                "mtg arena",
                "mtg arena new set",
                "mtg restricted list",
                "mtga",
                "new cards",
                "restricted cards mtg",
                "yugioh"
            ],
            "publish_time": "2024-11-01 09:00:19",
            "views": 62454,
            "sources": [
                "discord.gg",
                "join.dripshop.live",
                "tinyurl.com",
                "ultimateguard.com",
                "www.coolstuffinc.com",
                "www.instagram.com",
                "www.moxfield.com"
            ],
            "decks": [
                {
                    "metadata": {
                        "author": "CovertGoBlue",
                        "comments": 0,
                        "date": "2024-10-31",
                        "irregular_format": "none",
                        "likes": 1,
                        "name": "Honest Mono Red | Standard",
                        "source": "www.moxfield.com",
                        "url": "https://www.moxfield.com/decks/zhCBth2WREaMMYxP_VbSlQ",
                        "views": 202
                    },
                    "decklist_id": "caf71ff7-ab00-5f89-8ad8-a2c63a353e7c",
                    "decklist_extended_id": "b8bad2bd-dfe7-6a99-60d0-3351f16040cb"
                }
            ]
        },
        {
            "id": "_U5rEbaLZ-Y",
            "url": "https://www.youtube.com/watch?v=_U5rEbaLZ-Y",
            "author": "CovertGoBlue",
            "title": "Dimir Demons won the MTG World Championship!",
            "description": "Try Rocket Money for free: https://rocketmoney.com/covertblue\n#rocketmoney #personalfinance Sponsored by Rocket Money\n\nDecklist - https://www.moxfield.com/decks/P5JeOrjCQ0SYU489dX86Ag\n\nSponsors\n\nCoolStuffInc.com Promo Code CGB5 - https://www.coolstuffinc.com/cgb\nUltimate Guard - https://tinyurl.com/UGCGB\nDripShop.live - https://join.dripshop.live/CovertGoBlue\nMoxfield - https://www.moxfield.com/users/CovertGoBlue\n\nDiscord - https://discord.gg/MXt3DEP\nInstagram - https://www.instagram.com/covertgoblue/\n\nCredits\n\nWritten and performed by Daniel Wagner, aka CovertGoBlue\nEdited by @libmae_\nLogo design by HolyMTG - HolyMTG@gmail.com Twitter @HolyMTG\n© CovertGoBlue Entertainment, LLC\n\n#cgb #mtgarena #mtgstandard #dimir",
            "keywords": [
                "Best Deck",
                "Best MTG Deck",
                "CGB",
                "CGB Deck",
                "CGB Magic the Gathering",
                "Covert Go",
                "Covert Go Blue",
                "Covert Go MTG",
                "CovertGoBlue",
                "Deck",
                "Gameplay",
                "MTG Cards",
                "MTG Deck",
                "Mythic",
                "New Cards",
                "New Deck",
                "blb mtg arena",
                "covertgo",
                "covertgo mtg",
                "deck",
                "decks",
                "demons",
                "dimir demons",
                "dsk",
                "dsk early access",
                "dsk mtg",
                "duskmourn",
                "duskmourn early access",
                "duskmourn standard",
                "early access",
                "gameplay",
                "guide",
                "magic the gathering",
                "magic world championships",
                "mtg",
                "mtg arena",
                "mtg arena new set",
                "mtga",
                "new cards",
                "ub demons"
            ],
            "publish_time": "2024-10-31 09:00:44",
            "views": 52755,
            "sources": [
                "discord.gg",
                "join.dripshop.live",
                "rocketmoney.com",
                "tinyurl.com",
                "www.coolstuffinc.com",
                "www.instagram.com",
                "www.moxfield.com"
            ],
            "decks": [
                {
                    "metadata": {
                        "author": "CovertGoBlue",
                        "comments": 0,
                        "date": "2024-10-29",
                        "format": "standard",
                        "likes": 4,
                        "name": "UB Demons",
                        "source": "www.moxfield.com",
                        "url": "https://www.moxfield.com/decks/P5JeOrjCQ0SYU489dX86Ag",
                        "views": 2592
                    },
                    "decklist_id": "b5c7f4a6-1f0d-4a17-6533-b28e5ac7992c",
                    "decklist_extended_id": "095011e0-0121-6808-a950-ae835d9827e5"
                }
            ]
        }
    ]
}