{
    "id": "UCZAZTSd0xnor7hJFmINIBIw",
    "title": "MTGGoldfish",
    "description": "Magic the Gathering decks, reviews and product openings! The official channel for MTGGoldfish. Visit us at http://www.mtggoldfish.com.Upload schedule for Maj...",
    "tags": [
        "MTG",
        "Magic the Gathering",
        "mtggoldfish"
    ],
    "subscribers": 355000,
    "scrape_time": "2025-09-14 22:33:06",
    "videos": [
        {
            "id": "x6CEAVeVdW0",
            "author": "MTGGoldfish",
            "title": "This Is Not OK | Brewer's Kitchen",
            "description": "Brewer's Kitchen plays the most toxic land destruction deck he ever built. \n\nToday's video is brought to you by Card Kingdom. You can pick up some Magic: the Gathering cards (and help support the show) at https://www.cardkingdom.com/mtggoldfish\n\n► Read more about this deck (full article): https://www.mtggoldfish.com/articles/this-is-not-ok-brewer-s-kitchen\n► View this deck with the latest prices: https://www.mtggoldfish.com/deck/7338034#paper\n\n◼ Purchase this deck (paper): http://mtg.fish/JSPIg\n◼ Purchase this deck (Magic Online): http://mtg.fish/zxOms\n\n#MTG\n#MagicTheGathering\n#MTGBrawl",
            "keywords": [
                "Gameplay",
                "MTG",
                "MTG Arena",
                "Magic Arena",
                "Magic the Gathering"
            ],
            "publish_time": "2025-09-14 08:00:03",
            "views": 19214,
            "decks": [
                {
                    "metadata": {
                        "format": "brawl",
                        "author": "Brewer's Kitchen",
                        "date": "2025-09-11",
                        "url": "https://www.mtggoldfish.com/deck/7338034",
                        "name": "How Is This Even Legal?",
                        "custom_theme": "Wrenn and Six"
                    },
                    "decklist_id": "79e0cbe2-f84f-1fb8-fd33-f0c207538ba3",
                    "decklist_extended_id": "50dde416-5fa0-bb90-a5ce-9753f2d53a3b"
                },
                {
                    "metadata": {
                        "format": "brawl",
                        "author": "Brewer's Kitchen",
                        "date": "2025-09-11",
                        "container_url": "https://www.mtggoldfish.com/articles/this-is-not-ok-brewer-s-kitchen",
                        "url": "https://www.mtggoldfish.com/articles/this-is-not-ok-brewer-s-kitchen",
                        "name": "How Is This Even Legal?",
                        "custom_theme": "Wrenn and Six"
                    },
                    "decklist_id": "79e0cbe2-f84f-1fb8-fd33-f0c207538ba3",
                    "decklist_extended_id": "50dde416-5fa0-bb90-a5ce-9753f2d53a3b"
                }
            ]
        },
        {
            "id": "W0ZMuSPjjZ4",
            "author": "MTGGoldfish",
            "title": "Squall Out Equipments",
            "description": "Squall, SeeD Mercenary itself doesn't need to attack to get value! On top of that, with so many people playing artifact answers, its nice to reoccur them with Squall as well!\n\nToday's video is brought to you by Card Kingdom. You can pick up some Magic: the Gathering cards (and help support the show) at https://www.cardkingdom.com/mtggoldfish \n\n► Read more about this deck (full article): https://www.mtggoldfish.com/articles/single-scoop-squall-out-equipments\n► View this deck with the latest prices: https://www.mtggoldfish.com/deck/7331518#paper\n\n◼ Purchase this deck (paper): http://mtg.fish/5uvk1\n◼ Purchase this deck (Magic Online): http://mtg.fish/ue0IS\n\n#MTG\n#MagicTheGathering\n#MagicArena\n#MTGStandard",
            "keywords": [
                "Gameplay",
                "MTG",
                "MTG Arena",
                "Magic Arena",
                "Magic the Gathering"
            ],
            "publish_time": "2025-09-13 08:00:06",
            "views": 12879,
            "decks": [
                {
                    "metadata": {
                        "format": "standard",
                        "author": "TheAsianAvenger",
                        "date": "2025-09-07",
                        "url": "https://www.mtggoldfish.com/deck/7331518",
                        "name": "Squalliam"
                    },
                    "decklist_id": "63323a1b-8f23-7c4c-24e0-13f32291ebaa",
                    "decklist_extended_id": "b9eb3e4d-689b-dce0-2a3c-9b0a0ac679c4"
                },
                {
                    "metadata": {
                        "format": "standard",
                        "author": "TheAsianAvenger",
                        "date": "2025-09-07",
                        "container_url": "https://www.mtggoldfish.com/articles/single-scoop-squall-out-equipments",
                        "url": "https://www.mtggoldfish.com/articles/single-scoop-squall-out-equipments",
                        "name": "Squalliam"
                    },
                    "decklist_id": "63323a1b-8f23-7c4c-24e0-13f32291ebaa",
                    "decklist_extended_id": "b9eb3e4d-689b-dce0-2a3c-9b0a0ac679c4"
                }
            ]
        },
        {
            "id": "DKo32p7Opm4",
            "author": "MTGGoldfish",
            "title": "I Had a Very Expensive Random Encounter... | Much Abrew",
            "description": "We played a $20 budget build of Random Encounter a couple of months ago, but what if your Random Encounter budget was limitless?\n\nToday's video is brought to you by Card Kingdom. You can pick up some Magic: the Gathering cards (and help support the show) at https://www.cardkingdom.com/mtggoldfish\n\n► Read more about this deck (full article): https://www.mtggoldfish.com/articles/much-abrew-an-expensive-random-encounter-standard\n► View this deck with the latest prices: https://www.mtggoldfish.com/deck/7324556#paper\n\n◼ Purchase this deck (paper): http://mtg.fish/1oray\n◼ Purchase this deck (Magic Online): http://mtg.fish/oXyr6\n\n#MTG\n#MagicTheGathering\n#MagicArena\n#mtgstandard \n\n0:00 Start\n5:24 Games",
            "keywords": [
                "Gameplay",
                "MTG",
                "MTG Arena",
                "Magic Arena",
                "Magic the Gathering"
            ],
            "publish_time": "2025-09-12 08:08:00",
            "views": 49106,
            "decks": [
                {
                    "metadata": {
                        "format": "standard",
                        "author": "Scotty Fischer",
                        "date": "2025-09-02",
                        "container_url": "https://www.mtggoldfish.com/articles/much-abrew-an-expensive-random-encounter-standard",
                        "url": "https://www.mtggoldfish.com/articles/much-abrew-an-expensive-random-encounter-standard",
                        "name": "Random Encounter"
                    },
                    "decklist_id": "b99b3102-86a2-ca44-26a1-997215fb1176",
                    "decklist_extended_id": "ab156e84-a1c8-d38e-4cc1-f4e0cfecaf9a"
                },
                {
                    "metadata": {
                        "format": "standard",
                        "author": "Scotty Fischer",
                        "date": "2025-09-02",
                        "url": "https://www.mtggoldfish.com/deck/7324556",
                        "name": "Random Encounter"
                    },
                    "decklist_id": "b99b3102-86a2-ca44-26a1-997215fb1176",
                    "decklist_extended_id": "ab156e84-a1c8-d38e-4cc1-f4e0cfecaf9a"
                }
            ]
        },
        {
            "id": "6RxBgm7omgk",
            "author": "MTGGoldfish",
            "title": "This Deck of Legends Won Way More Than It Should",
            "description": "Is the meta too fast for a deck full of Legends? Yes ...but this deck pulled out a chunk of hilarious victories that we probably shouldn't have won.\n\nToday's video is brought to you by Card Kingdom. You can pick up some Magic: the Gathering cards (and help support the show) at https://www.cardkingdom.com/mtggoldfish\n\n► Read more about this deck (full article): https://www.mtggoldfish.com/articles/single-scoop-this-deck-of-legends-won-way-more-than-it-should\n► View this deck with the latest prices: https://www.mtggoldfish.com/deck/7331338#paper\n\n◼ Purchase this deck (paper): http://mtg.fish/s4yrb\n◼ Purchase this deck (Magic Online): http://mtg.fish/HNEsD\n\n#MTG\n#MagicTheGathering\n#MagicArena\n#MTGStandard",
            "keywords": [
                "Gameplay",
                "MTG",
                "MTG Arena",
                "Magic Arena",
                "Magic the Gathering"
            ],
            "publish_time": "2025-09-11 08:00:08",
            "views": 19188,
            "decks": [
                {
                    "metadata": {
                        "format": "standard",
                        "author": "TheAsianAvenger",
                        "date": "2025-09-07",
                        "url": "https://www.mtggoldfish.com/deck/7331338",
                        "name": "Legendary"
                    },
                    "decklist_id": "5fc0f0d5-73f0-0000-0889-2647aa251c85",
                    "decklist_extended_id": "d64b5f64-065f-919c-5d4f-52775a213367"
                },
                {
                    "metadata": {
                        "format": "standard",
                        "author": "TheAsianAvenger",
                        "date": "2025-09-07",
                        "container_url": "https://www.mtggoldfish.com/articles/single-scoop-this-deck-of-legends-won-way-more-than-it-should",
                        "url": "https://www.mtggoldfish.com/articles/single-scoop-this-deck-of-legends-won-way-more-than-it-should",
                        "name": "Legendary"
                    },
                    "decklist_id": "5fc0f0d5-73f0-0000-0889-2647aa251c85",
                    "decklist_extended_id": "d64b5f64-065f-919c-5d4f-52775a213367"
                }
            ]
        }
    ]
}