{
    "id": "UCZAZTSd0xnor7hJFmINIBIw",
    "title": "MTGGoldfish",
    "description": "Magic the Gathering decks, reviews and product openings! The official channel for MTGGoldfish. Visit us at http://www.mtggoldfish.com.\n\nUpload schedule for Major Series:\nSunday: Meme or Dream? \nMonday: Budget Magic, MTGGoldfish Podcast\nTuesday: Arena Series with Crim\nWednesday: Against the Odds\nThursday: Arena Series with Crim\nFriday: Much Abrew About Nothing\nSaturday: Arena Series with Crim",
    "tags": [
        "MTG",
        "Magic the Gathering",
        "mtggoldfish"
    ],
    "subscribers": 348000,
    "scrape_time": "2025-07-04 02:04:21",
    "videos": [
        {
            "id": "8PgCqBkXin8",
            "url": "https://www.youtube.com/watch?v=8PgCqBkXin8",
            "author": "MTGGoldfish",
            "title": "Zell Dincht Has A Cute Land Loop",
            "description": "Zell Dincht can keep looping a land. Is it a win more? Yes. Is it absurdly fun? Also yes.\n\nToday's video is brought to you by Card Kingdom. You can pick up some Magic: the Gathering cards (and help support the show) at https://www.cardkingdom.com/mtggoldfish\n\n► Read more about this deck (full article): https://www.mtggoldfish.com/articles/single-scoop-zell-dincht-has-a-cute-land-loop\n► View this deck with the latest prices: https://www.mtggoldfish.com/deck/7200012#paper\n\n◼ Purchase this deck (paper): http://mtg.fish/Sjiux\n◼ Purchase this deck (Magic Online): http://mtg.fish/Tj6Js\n\n#MTG\n#MagicTheGathering\n#MagicArena\n#MTGStandard",
            "keywords": [
                "Gameplay",
                "MTG",
                "MTG Arena",
                "Magic Arena",
                "Magic the Gathering"
            ],
            "publish_time": "2025-07-03 08:00:05",
            "views": 13670,
            "sources": [
                "mtg.fish",
                "www.cardkingdom.com",
                "www.mtggoldfish.com"
            ],
            "decks": [
                {
                    "metadata": {
                        "author": "TheAsianAvenger",
                        "container_url": "https://www.mtggoldfish.com/articles/single-scoop-zell-dincht-has-a-cute-land-loop",
                        "date": "2025-06-27",
                        "format": "standard",
                        "name": "Zell Loves Lindblum",
                        "source": "www.mtggoldfish.com",
                        "url": "https://www.mtggoldfish.com/articles/single-scoop-zell-dincht-has-a-cute-land-loop"
                    },
                    "decklist_id": "7a545020-cfad-64e7-17a2-6eab9994a6cb",
                    "decklist_extended_id": "efc60c53-9e91-cf7f-207d-1bcd5121ee7f"
                },
                {
                    "metadata": {
                        "author": "TheAsianAvenger",
                        "date": "2025-06-27",
                        "format": "standard",
                        "name": "Zell Loves Lindblum",
                        "source": "www.mtggoldfish.com",
                        "url": "https://www.mtggoldfish.com/deck/7200012"
                    },
                    "decklist_id": "7a545020-cfad-64e7-17a2-6eab9994a6cb",
                    "decklist_extended_id": "efc60c53-9e91-cf7f-207d-1bcd5121ee7f"
                }
            ]
        }
    ]
}