{
    "url": "https://www.youtube.com/@MTGGoldfish",
    "id": "UCZAZTSd0xnor7hJFmINIBIw",
    "title": "MTGGoldfish",
    "description": "Magic the Gathering decks, reviews and product openings! The official channel for MTGGoldfish. Visit us at http://www.mtggoldfish.com.\n\nUpload schedule for Major Series:\nSunday: Meme or Dream? \nMonday: Budget Magic, MTGGoldfish Podcast\nTuesday: Arena Series with Crim\nWednesday: Against the Odds\nThursday: Arena Series with Crim\nFriday: Much Abrew About Nothing\nSaturday: Arena Series with Crim",
    "tags": [
        "MTG",
        "Magic the Gathering",
        "mtggoldfish"
    ],
    "subscribers": 324000,
    "scrape_time": "2024-08-28 00:30:09",
    "videos": [
        {
            "id": "sEAd6duNLts",
            "url": "https://www.youtube.com/watch?v=sEAd6duNLts",
            "author": "MTGGoldfish",
            "title": "Keeping Aggro Decks Honest in Standard",
            "description": "Whenever aggro runs a little too wild in best of one, its always time to dust off the most narrow deck of them all. The ol' anti-aggro mono white! We even got new tools thanks to Bloomburrow!\n\nToday's video is brought to you by Card Kingdom. You can pick up some Magic: the Gathering cards (and help support the show) at https://www.cardkingdom.com/mtggoldfish\n\n► Read more about this deck (full article): https://www.mtggoldfish.com/articles/single-scoop-keeping-aggro-decks-honest\n► View this deck with the latest prices: https://www.mtggoldfish.com/deck/6588094#paper\n\n◼ Purchase this deck (paper): http://mtg.fish/pTh18\n◼ Purchase this deck (Magic Online): http://mtg.fish/9Z5T2\n\n#MTG\n#MagicTheGathering\n#MagicArena\n#MTGStandard",
            "keywords": [
                "Gameplay",
                "MTG",
                "MTG Arena",
                "Magic Arena",
                "Magic the Gathering"
            ],
            "publish_time": "2024-08-27 08:00:07",
            "views": 12282,
            "sources": [
                "mtg.fish",
                "www.cardkingdom.com",
                "www.mtggoldfish.com"
            ],
            "derived_format": "standard",
            "decks": [
                {
                    "metadata": {
                        "author": "TheAsianAvenger",
                        "date": "2024-08-21",
                        "format": "standard",
                        "name": "Red Gamer Check",
                        "source": "www.mtggoldfish.com",
                        "url": "https://www.mtggoldfish.com/deck/6588094"
                    },
                    "decklist_id": "648e4dc6-7b99-3e5b-90e4-e361fbb8e72a",
                    "decklist_extended_id": "c442c06e-84de-e264-cae9-b1730ec27481"
                }
            ]
        },
        {
            "id": "7FgoupYYgs4",
            "url": "https://www.youtube.com/watch?v=7FgoupYYgs4",
            "author": "MTGGoldfish",
            "title": "The Birden of Birds  Standard",
            "description": "THE BIRDEMIC IS HERE. We've got a ton of fun birds in this UW style tempo deck!\n\nToday's video is brought to you by Card Kingdom. You can pick up some Magic: the Gtahering cards (and help support the show) at https:?/www.cardkingdom.com/mtggoldfish\n\n► Read more about this deck (full article): https://www.mtggoldfish.com/articles/single-scoop-the-birden-of-birds\n► View this deck with the latest prices: https://www.mtggoldfish.com/deck/6546620#paper\n\n◼ Purchase this deck (paper): http://mtg.fish/PYdMX\n◼ Purchase this deck (Magic Online): http://mtg.fish/E34AJ\n\n#MTG\n#MagicTheGathering\n#MagicArena\n#MTGStandard",
            "keywords": [
                "Gameplay",
                "MTG",
                "MTG Arena",
                "Magic Arena",
                "Magic the Gathering"
            ],
            "publish_time": "2024-08-06 08:00:05",
            "views": 27113,
            "sources": [
                "mtg.fish",
                "www.mtggoldfish.com"
            ],
            "derived_format": "standard",
            "decks": [
                {
                    "metadata": {
                        "author": "TheAsianAvenger",
                        "date": "2024-07-31",
                        "format": "standard",
                        "name": "Birbs",
                        "source": "www.mtggoldfish.com",
                        "url": "https://www.mtggoldfish.com/deck/6546620"
                    },
                    "decklist_id": "22651f2c-f6e7-7fc9-c62e-6fd4a9da648b",
                    "decklist_extended_id": "e2c27e84-65bb-497b-2239-805748d9d242"
                }
            ]
        },
        {
            "id": "B1nFsCtFMJI",
            "url": "https://www.youtube.com/watch?v=B1nFsCtFMJI",
            "author": "MTGGoldfish",
            "title": "The Mythic Turn 3 Kill Budget Deck for Bloomburrow Standard",
            "description": "Only 16 Rares. Just $80. Consistent turn three kills! Can we hit mythic with a budget friendly Rakdos Fling deck in Bloomburrow Standard? Let's find out!\n\nToday's video is brought to you by Card Kingdom. You can pick up some Magic: the Gathering cards (and help support the show) at https://www.cardkingdom.com/mtggoldfish\n\n► Read more about this deck (full article): https://www.mtggoldfish.com/articles/budget-magic-80-16-rare-rakdos-fling-standard\n► View this deck with the latest prices: https://www.mtggoldfish.com/deck/6555568#paper\n\n◼ Purchase this deck (paper): http://mtg.fish/RGSQw\n◼ Purchase this deck (Magic Online): http://mtg.fish/laqFV\n\n#MTG\n#MagicTheGathering\n#MagicArena\n#mtgstandard \n\n0:00 Start\n4:15 Games",
            "keywords": [
                "MTG",
                "MTG Arena",
                "MTGGoldfish",
                "Magic: the Gathering"
            ],
            "publish_time": "2024-08-05 08:00:06",
            "views": 69988,
            "sources": [
                "mtg.fish",
                "www.cardkingdom.com",
                "www.mtggoldfish.com"
            ],
            "derived_format": "standard",
            "decks": [
                {
                    "metadata": {
                        "author": "Highwalker",
                        "date": "2024-08-04",
                        "format": "standard",
                        "name": "Rakdos Fling",
                        "source": "www.mtggoldfish.com",
                        "url": "https://www.mtggoldfish.com/deck/6555568"
                    },
                    "decklist_id": "84b35122-3e50-b03c-6e04-1141b08fec17",
                    "decklist_extended_id": "b9adee17-d180-a7a8-3584-4e69c20c7dcf"
                }
            ]
        },
        {
            "id": "LB7N3L44Nwg",
            "url": "https://www.youtube.com/watch?v=LB7N3L44Nwg",
            "author": "MTGGoldfish",
            "title": "Bats Have Their Own Bitterblossom?  Bloomburrow Standard",
            "description": "Bats love losing and gaining life and they even have their own Bat-terblossom to generate a Bat army?\n\nToday's video is brought to you by Card Kingdom. You can pick up some Magic: the Gathering cards (and help support the show) at https://www.cardkingdom.com/mtggoldfish\n\n► Read more about this deck (full article): https://www.mtggoldfish.com/articles/single-scoop-bats-have-their-own-bitterblossom\n► View this deck with the latest prices: https://www.mtggoldfish.com/deck/6546621#paper\n\n◼ Purchase this deck (paper): http://mtg.fish/KpuoR\n◼ Purchase this deck (Magic Online): http://mtg.fish/SxGQ7\n\n#MTG\n#MagicTheGathering\n#MagicArena\n#MTGStandard",
            "keywords": [
                "Gameplay",
                "MTG",
                "MTG Arena",
                "Magic Arena",
                "Magic the Gathering"
            ],
            "publish_time": "2024-08-03 08:00:04",
            "views": 45431,
            "sources": [
                "mtg.fish",
                "www.cardkingdom.com",
                "www.mtggoldfish.com"
            ],
            "derived_format": "standard",
            "decks": [
                {
                    "metadata": {
                        "author": "TheAsianAvenger",
                        "date": "2024-07-31",
                        "format": "standard",
                        "name": "Batzmaru",
                        "source": "www.mtggoldfish.com",
                        "url": "https://www.mtggoldfish.com/deck/6546621"
                    },
                    "decklist_id": "4e7c1f7e-ea0d-b240-8e27-4c447d51eaaa",
                    "decklist_extended_id": "7dcabc68-d02f-f60d-76e1-4a771e864ec9"
                }
            ]
        },
        {
            "id": "yHIe_YyXLqY",
            "url": "https://www.youtube.com/watch?v=yHIe_YyXLqY",
            "author": "MTGGoldfish",
            "title": "8 Rack Discard, but in Bloomburrow Standard  Much Abrew",
            "description": "Does Bandit's Talent mean we can build an 8 Rack style discard deck in Standard? Let's find out!\n\nToday's video is brought to you by Card Kingdom. You can pick up some Magic: the Gathering cards (and help support the show) at https://www.cardkingdom.com/mtggoldfish\n\n► Read more about this deck (full article): https://www.mtggoldfish.com/articles/much-abrew-8-rack-discard-but-in-standard-bloomburrow\n► View this deck with the latest prices: https://www.mtggoldfish.com/deck/6524359#paper\n\n◼ Purchase this deck (paper): http://mtg.fish/TS7hK\n◼ Purchase this deck (Magic Online): http://mtg.fish/TQH6p\n\n#MTG\n#MagicTheGathering\n#MagicArena\n#mtgstandard \n\n0:00 Start\n4:11 Games",
            "keywords": [
                "Gameplay",
                "MTG",
                "MTG Arena",
                "Magic Arena",
                "Magic the Gathering"
            ],
            "publish_time": "2024-08-02 08:00:08",
            "views": 79493,
            "sources": [
                "mtg.fish",
                "www.cardkingdom.com",
                "www.mtggoldfish.com"
            ],
            "derived_format": "standard",
            "decks": [
                {
                    "metadata": {
                        "author": "SaffronOlive",
                        "date": "2024-07-20",
                        "format": "standard",
                        "name": "Standard 8 Rack",
                        "source": "www.mtggoldfish.com",
                        "url": "https://www.mtggoldfish.com/deck/6524359"
                    },
                    "decklist_id": "bd6247d7-b2a4-6643-3e71-ec8c1fbc1e42",
                    "decklist_extended_id": "125f4cbb-5b0f-7700-5ad3-cbf96b187f69"
                }
            ]
        },
        {
            "id": "7-KhHj_RcTo",
            "url": "https://www.youtube.com/watch?v=7-KhHj_RcTo",
            "author": "MTGGoldfish",
            "title": "Maha Blast  Bloomburrow Standard",
            "description": "Its feathers night and Maha is looking to be a part of the new Mono Black deck with Harvester of Misery!\n\nToday's video is brought to you by Card Kingdom. You can pick up some Magic: the Gathering cards (and help support the show) at https://www.cardkingdom.com/mtggoldfish\n\n► Read more about this deck (full article): https://www.mtggoldfish.com/articles/single-scoop-maha-blast\n► View this deck with the latest prices: https://www.mtggoldfish.com/deck/6532925#paper\n\n◼ Purchase this deck (paper): http://mtg.fish/2Y9Us\n◼ Purchase this deck (Magic Online): http://mtg.fish/EjIk2\n\n#MTG\n#MagicTheGathering\n#MagicArena\n#MTGStandard",
            "keywords": [
                "Gameplay",
                "MTG",
                "MTG Arena",
                "Magic Arena",
                "Magic the Gathering"
            ],
            "publish_time": "2024-08-01 08:00:12",
            "views": 36089,
            "sources": [
                "mtg.fish",
                "www.cardkingdom.com",
                "www.mtggoldfish.com"
            ],
            "derived_format": "standard",
            "decks": [
                {
                    "metadata": {
                        "author": "TheAsianAvenger",
                        "date": "2024-07-25",
                        "format": "standard",
                        "name": "Maha Blast",
                        "source": "www.mtggoldfish.com",
                        "url": "https://www.mtggoldfish.com/deck/6532925"
                    },
                    "decklist_id": "1a50803d-28cd-68c6-5dd2-8c6b4690b3a4",
                    "decklist_extended_id": "741d4354-92a2-19a9-5b2a-7ab7280fde6a"
                }
            ]
        },
        {
            "id": "QZbTfH7UMOE",
            "url": "https://www.youtube.com/watch?v=QZbTfH7UMOE",
            "author": "MTGGoldfish",
            "title": "I Make The Most Otters Ever, and They're Insidious  Against the Odds",
            "description": "What are the odds of using the combo of Stormsplitter and Insidious Roots to make the most otters ever in Bloomburrow Standard? Let's find out!\n\nToday's video is brought to you by Card Kingdom. You can pick up some Magic: the Gathering cards (and help support the show) at https://www.cardkingdom.com/mtggoldfish\n\n► Read more about this deck (full article): https://www.mtggoldfish.com/articles/against-the-odds-insidious-otter-storm-bloomburrow-standard\n► View this deck with the latest prices: https://www.mtggoldfish.com/deck/6528253#paper\n\n◼ Purchase this deck (paper): http://mtg.fish/nslRf\n◼ Purchase this deck (Magic Online): http://mtg.fish/H8zdt\n\n#MTG\n#MagicTheGathering\n#magicarena \n#mtgstandard \n\n0:00 Start\n4:25 Games",
            "keywords": [
                "Gameplay",
                "MTG",
                "MTG Arena",
                "Magic Arena",
                "Magic the Gathering"
            ],
            "publish_time": "2024-07-31 08:00:08",
            "views": 78890,
            "sources": [
                "mtg.fish",
                "www.cardkingdom.com",
                "www.mtggoldfish.com"
            ],
            "derived_format": "standard",
            "decks": [
                {
                    "metadata": {
                        "author": "SaffronOlive",
                        "date": "2024-07-22",
                        "format": "standard",
                        "name": "Insidious Otter Storm",
                        "source": "www.mtggoldfish.com",
                        "url": "https://www.mtggoldfish.com/deck/6528253"
                    },
                    "decklist_id": "b5261d32-832f-71fb-3890-2a1976ae697c",
                    "decklist_extended_id": "30730528-548b-51fc-a5a9-78b6d089ed2f"
                }
            ]
        },
        {
            "id": "PZIB87vtz0w",
            "url": "https://www.youtube.com/watch?v=PZIB87vtz0w",
            "author": "MTGGoldfish",
            "title": "Lizards Are Hyper Aggro  Bloomburrow Standard",
            "description": "The new Burning Tree Emissary is a Lizard?? Who would've guessed Lizards would pack this much aggression in Standard!\n\nToday's video is brought to you by Card Kingdom. You can pick up some Magic: the Gathering cards (and help support the show) at https://www.cardkingdom.com/mtggoldfish\n\n► Read more about this deck (full article): https://www.mtggoldfish.com/articles/single-scoops-lizards-are-hyper-aggro\n► View this deck with the latest prices: https://www.mtggoldfish.com/deck/6532928#paper\n\n◼ Purchase this deck (paper): http://mtg.fish/HMavm\n◼ Purchase this deck (Magic Online): http://mtg.fish/lVbjG\n\n#MTG\n#MagicTheGathering\n#MagicArena\n#MTGStandard",
            "keywords": [
                "Gameplay",
                "MTG",
                "MTG Arena",
                "Magic Arena",
                "Magic the Gathering"
            ],
            "publish_time": "2024-07-30 08:00:07",
            "views": 34816,
            "sources": [
                "mtg.fish",
                "www.cardkingdom.com",
                "www.mtggoldfish.com"
            ],
            "derived_format": "standard",
            "decks": [
                {
                    "metadata": {
                        "author": "TheAsianAvenger",
                        "date": "2024-07-25",
                        "format": "standard",
                        "name": "Lizards",
                        "source": "www.mtggoldfish.com",
                        "url": "https://www.mtggoldfish.com/deck/6532928"
                    },
                    "decklist_id": "85919d58-7832-f1d9-a285-9e452f32381c",
                    "decklist_extended_id": "e9180eaa-3af2-b340-24ac-658e5b20dccf"
                }
            ]
        },
        {
            "id": "97vQrJyLoN8",
            "url": "https://www.youtube.com/watch?v=97vQrJyLoN8",
            "author": "MTGGoldfish",
            "title": "$60 Big Red  Bloomburrow Standard Budget Magic",
            "description": "Is going big the right way to build Mono-Red in Bloomburrow on a 14 rare/$60 budget? Let's find out!\n\n#ad Don’t miss the new Deadpool and Wolverine themed mode and limited login rewards in MARVEL SNAP! Use my link to download the game and play! https://www.inflcr.co/SHKcD\n\nToday's video is brought to you by Card Kingdom. You can pick up some Magic: the Gathering cards (and help support the show) at https://www.cardkingdom.com/mtggoldfish\n\n► Read more about this deck (full article): https://www.mtggoldfish.com/articles/budget-magic-60-14-rare-big-red-bloomburrow-standard\n► View this deck with the latest prices: https://www.mtggoldfish.com/deck/6524268#paper\n\n◼ Purchase this deck (paper): http://mtg.fish/bPWHM\n◼ Purchase this deck (Magic Online): http://mtg.fish/2W1Rb\n\n#MTG\n#MagicTheGathering\n#MagicArena\n#mtgstandard \n\n0:00 Start\n5:20 Games",
            "keywords": [
                "Gameplay",
                "MTG",
                "MTG Arena",
                "Magic Arena",
                "Magic the Gathering"
            ],
            "publish_time": "2024-07-29 08:00:05",
            "views": 59730,
            "sources": [
                "mtg.fish",
                "www.cardkingdom.com",
                "www.inflcr.co",
                "www.mtggoldfish.com"
            ],
            "derived_format": "standard",
            "decks": [
                {
                    "metadata": {
                        "author": "SaffronOlive",
                        "date": "2024-07-20",
                        "format": "standard",
                        "name": "BLB BUDGET Big Red",
                        "source": "www.mtggoldfish.com",
                        "url": "https://www.mtggoldfish.com/deck/6524268"
                    },
                    "decklist_id": "19aadea4-8ebd-9395-35c9-a41a21122d13",
                    "decklist_extended_id": "51283160-86d5-68b0-94c5-f322d64bbc73"
                }
            ]
        }
    ]
}