{
    "id": "UCd0kth9C1hqJiaoedeBZ0cQ",
    "title": "LegenVD",
    "description": "Magic the Gathering strategy videos with a focus on the digital Magic Arena.\nThis channel is supported by its fans on Patreon: https://www.patreon.com/LegenVD",
    "tags": [
        "MTG",
        "Magic the gathering",
        "arena",
        "brawl",
        "card game",
        "commander",
        "deck",
        "dragonstorm",
        "edh",
        "educational",
        "explorer",
        "gameplay",
        "historic",
        "how to",
        "magic arena",
        "mtg arena",
        "mythic",
        "standard",
        "strategy",
        "tarkir",
        "timeless",
        "tips",
        "tutorial"
    ],
    "subscribers": 136000,
    "scrape_time": "2025-05-06 02:32:38",
    "videos": [
        {
            "id": "M6kQHzL0Ms0",
            "url": "https://www.youtube.com/watch?v=M6kQHzL0Ms0",
            "author": "LegenVD",
            "title": "My new favorite Standard combo.",
            "description": "Magic: The Gathering Arena gameplay with a jeskai combo deck ft. Three Blind Mice and Shiko, Paragon of the Way in Standard.\n\nPatreon: https://www.patreon.com/LegenVD\n\n00:00 - Deck Tech\n03:58 - Match 1\n07:06 - Match 2\n25:44 - Match 3\n29:45 - Match 4\n35:32 - Match 5\n38:08 - Match 6\n42:33 - Match 7\n\nDecklist:\nhttps://aetherhub.com/Deck/shiko-token-combo\n\n\"Movement Proposition\" Kevin MacLeod (incompetech.com)\nLicensed under Creative Commons: By Attribution 4.0 License\nhttp://creativecommons.org/licenses/by/4.0/\n\nUnofficial Fan Content permitted under the Fan Content Policy. Not approved/endorsed by Wizards. Portions of the materials used are property of Wizards of the Coast. ©Wizards of the Coast LLC.\n\n#mtgarena #tarkir #mtg #mtgtarkir #mtgtdm #magicthegathering",
            "keywords": [
                "Standard MTG",
                "blue",
                "caretaker's talent",
                "combo",
                "copy",
                "deck",
                "decks",
                "dragonstorm",
                "gameplay",
                "guide",
                "infinite",
                "jeskai",
                "jeskai control",
                "legend",
                "lvd",
                "magic the gathering",
                "mouse",
                "mtg",
                "mtg arena",
                "mtga",
                "new standard",
                "rabbit",
                "red",
                "shiko",
                "standard",
                "standard deck",
                "tarkir",
                "tarkir dragonstorm",
                "tarkir standard",
                "tdm",
                "tdm standard",
                "three blind mice",
                "tokens",
                "white"
            ],
            "publish_time": "2025-05-05 09:00:26",
            "views": 15572,
            "sources": [
                "aetherhub.com",
                "arena.decklist",
                "creativecommons.org",
                "www.patreon.com"
            ],
            "decks": [
                {
                    "metadata": {
                        "archetype": "control",
                        "author": "LegenVD",
                        "comments": 0,
                        "date": "2025-05-05",
                        "exports": 198,
                        "format": "standard",
                        "mode": "Bo1",
                        "name": "Shiko Token Combo",
                        "source": "aetherhub.com",
                        "url": "https://aetherhub.com/Deck/shiko-token-combo",
                        "views": 470
                    },
                    "decklist_id": "560a42f9-ca1c-36d1-4cb8-2c646739f558",
                    "decklist_extended_id": "ce60a14d-4f2d-0f5b-6a94-bea1d4a93cbd"
                }
            ]
        }
    ]
}